{
	"name": "00_Load_RetailSiteMaster",
	"properties": {
		"activities": [
			{
				"name": "Stage_RetailSiteMaster",
				"type": "ExecutePipeline",
				"dependsOn": [],
				"policy": {
					"secureInput": false
				},
				"userProperties": [],
				"typeProperties": {
					"pipeline": {
						"referenceName": "Stage_RetailSiteMaster",
						"type": "PipelineReference"
					},
					"waitOnCompletion": true
				}
			},
			{
				"name": "Load_RetailSiteMaster",
				"type": "ExecutePipeline",
				"dependsOn": [
					{
						"activity": "Stage_RetailSiteMaster",
						"dependencyConditions": [
							"Succeeded"
						]
					}
				],
				"policy": {
					"secureInput": false
				},
				"userProperties": [],
				"typeProperties": {
					"waitOnCompletion": true
				}
			}
		],
		"folder": {
			"name": "Site_Master/New_Model"
		},
		"annotations": []
	}
}