{
	"name": "00_Load_RetailSiteMaster_Incremental",
	"properties": {
		"activities": [
			{
				"name": "GetNewLoadId",
				"type": "Lookup",
				"dependsOn": [
					{
						"activity": "Preserve_WebUI_CompanyCode",
						"dependencyConditions": [
							"Succeeded"
						]
					}
				],
				"policy": {
					"timeout": "0.12:00:00",
					"retry": 0,
					"retryIntervalInSeconds": 30,
					"secureOutput": false,
					"secureInput": false
				},
				"userProperties": [],
				"typeProperties": {
					"source": {
						"type": "AzureSqlSource",
						"sqlReaderQuery": "DECLARE @RETURN_VALUE_ARGUMENT DECIMAL\r\nEXECUTE [dbo].[GET_NEW_LOADID]\r\n@RETURN_VALUE_ARGUMENT OUTPUT\r\n,@P_DATA_LOCATION_NAME = 'Retail_SiteMaster'\r\n,@P_PROGRAM_NAME = 'RetailSiteDataLoad'\r\n,@P_LOAD_DESCRIPTION = 'RetailSiteDataLoad'\r\n,@P_USERNAME = 'semadmin'\r\nSELECT @RETURN_VALUE_ARGUMENT AS RETURN_VALUE_ARGUMENT",
						"queryTimeout": "02:00:00",
						"partitionOption": "None"
					},
					"dataset": {
						"referenceName": "Semarchy_Repo",
						"type": "DatasetReference"
					}
				}
			},
			{
				"name": "SetNewLoadId",
				"type": "SetVariable",
				"dependsOn": [
					{
						"activity": "GetNewLoadId",
						"dependencyConditions": [
							"Succeeded"
						]
					}
				],
				"policy": {
					"secureOutput": false,
					"secureInput": false
				},
				"userProperties": [],
				"typeProperties": {
					"variableName": "LoadID",
					"value": {
						"value": "@{activity('GetNewLoadId').output.firstRow.RETURN_VALUE_ARGUMENT}",
						"type": "Expression"
					}
				}
			},
			{
				"name": "Preserve_WebUI_CompanyCode",
				"type": "Copy",
				"dependsOn": [],
				"policy": {
					"timeout": "0.12:00:00",
					"retry": 0,
					"retryIntervalInSeconds": 30,
					"secureOutput": false,
					"secureInput": false
				},
				"userProperties": [],
				"typeProperties": {
					"source": {
						"type": "AzureSqlSource",
						"sqlReaderQuery": "SELECT DISTINCT \n          LEGAL_ENTITY_ID,\n          LIC_CONTACT, \n          COMPANY_CODE,\n\t\t  GetDate() as LOAD_DATE\nFROM DBO.GD_LEGAL_ENTITY WITH(NOLOCK)",
						"queryTimeout": "02:00:00",
						"partitionOption": "None"
					},
					"sink": {
						"type": "AzureSqlSink",
						"preCopyScript": "TRUNCATE TABLE [EDW].[RSM_LicContact_CompanyCode]",
						"writeBehavior": "insert",
						"sqlWriterUseTableLock": false,
						"disableMetricsCollection": false
					},
					"enableStaging": false,
					"translator": {
						"type": "TabularTranslator",
						"mappings": [
							{
								"source": {
									"name": "LEGAL_ENTITY_ID",
									"type": "Decimal",
									"physicalType": "decimal",
									"scale": 0,
									"precision": 10
								},
								"sink": {
									"name": "LEGAL_ENTITY_ID",
									"type": "Decimal",
									"physicalType": "decimal",
									"scale": 0,
									"precision": 10
								}
							},
							{
								"source": {
									"name": "LIC_CONTACT",
									"type": "String",
									"physicalType": "nvarchar"
								},
								"sink": {
									"name": "LIC_CONTACT",
									"type": "String",
									"physicalType": "varchar"
								}
							},
							{
								"source": {
									"name": "COMPANY_CODE",
									"type": "String",
									"physicalType": "nvarchar"
								},
								"sink": {
									"name": "COMPANY_CODE",
									"type": "String",
									"physicalType": "varchar"
								}
							},
							{
								"source": {
									"name": "LOAD_DATE",
									"type": "DateTime",
									"physicalType": "datetime"
								},
								"sink": {
									"name": "LOAD_DATE",
									"type": "DateTime",
									"physicalType": "datetime"
								}
							}
						],
						"typeConversion": true,
						"typeConversionSettings": {
							"allowDataTruncation": true,
							"treatBooleanAsNumber": false
						}
					}
				},
				"inputs": [
					{
						"referenceName": "Retail_SiteMaster_GD_LEGAL_ENTITY",
						"type": "DatasetReference"
					}
				],
				"outputs": [
					{
						"referenceName": "EDW_RSM_LicContact_CompanyCode",
						"type": "DatasetReference"
					}
				]
			},
			{
				"name": "sub_LoadSiteIncremental",
				"type": "ExecutePipeline",
				"dependsOn": [
					{
						"activity": "SetNewLoadId",
						"dependencyConditions": [
							"Succeeded"
						]
					}
				],
				"policy": {
					"secureInput": false
				},
				"userProperties": [],
				"typeProperties": {
					"pipeline": {
						"referenceName": "00_01_LoadSiteIncremental",
						"type": "PipelineReference"
					},
					"waitOnCompletion": true,
					"parameters": {
						"B_LOADID": {
							"value": "@variables('LoadID')",
							"type": "Expression"
						}
					}
				}
			},
			{
				"name": "SubmitLoad",
				"type": "SqlServerStoredProcedure",
				"dependsOn": [
					{
						"activity": "sub_LoadTracking",
						"dependencyConditions": [
							"Succeeded"
						]
					}
				],
				"policy": {
					"timeout": "0.12:00:00",
					"retry": 0,
					"retryIntervalInSeconds": 30,
					"secureOutput": false,
					"secureInput": false
				},
				"userProperties": [],
				"typeProperties": {
					"storedProcedureName": "[dbo].[SUBMIT_LOAD]",
					"storedProcedureParameters": {
						"P_INTEGRATION_JOB_NAME": {
							"value": {
								"value": "RetailSiteDataLoad",
								"type": "Expression"
							},
							"type": "String"
						},
						"P_LOAD_ID": {
							"value": {
								"value": "@variables('LoadID')",
								"type": "Expression"
							},
							"type": "Decimal"
						},
						"P_USERNAME": {
							"value": {
								"value": "semadmin",
								"type": "Expression"
							},
							"type": "String"
						},
						"return_value_argument": {
							"value": null,
							"type": "Decimal"
						}
					}
				},
				"linkedServiceName": {
					"referenceName": "semarchy_repo",
					"type": "LinkedServiceReference"
				}
			},
			{
				"name": "sub_LoadLegalEntityIncremental",
				"type": "ExecutePipeline",
				"dependsOn": [
					{
						"activity": "sub_LoadSiteIncremental",
						"dependencyConditions": [
							"Succeeded"
						]
					}
				],
				"policy": {
					"secureInput": false
				},
				"userProperties": [],
				"typeProperties": {
					"pipeline": {
						"referenceName": "00_02_LoadLegalEntityIncremental",
						"type": "PipelineReference"
					},
					"waitOnCompletion": true,
					"parameters": {
						"B_LOADID": {
							"value": "@variables('LoadID')",
							"type": "Expression"
						}
					}
				}
			},
			{
				"name": "sub_LoadTracking",
				"type": "ExecutePipeline",
				"dependsOn": [
					{
						"activity": "sub_LoadLegalEntityIncremental",
						"dependencyConditions": [
							"Succeeded"
						]
					}
				],
				"policy": {
					"secureInput": false
				},
				"userProperties": [],
				"typeProperties": {
					"pipeline": {
						"referenceName": "00_03_LoadTracking",
						"type": "PipelineReference"
					},
					"waitOnCompletion": true,
					"parameters": {
						"B_LOADID": {
							"value": "@variables('LoadID')",
							"type": "Expression"
						}
					}
				}
			}
		],
		"variables": {
			"LoadID": {
				"type": "String"
			}
		},
		"folder": {
			"name": "Site_Master/New_Model"
		},
		"annotations": []
	}
}