{
	"name": "Load_ProductMasterLoad_Retail_Delete_PIM_EDW",
	"properties": {
		"activities": [
			{
				"name": "GetNewLoadId",
				"type": "Lookup",
				"dependsOn": [],
				"policy": {
					"timeout": "0.12:00:00",
					"retry": 0,
					"retryIntervalInSeconds": 30,
					"secureOutput": false,
					"secureInput": false
				},
				"userProperties": [],
				"typeProperties": {
					"source": {
						"type": "AzureSqlSource",
						"sqlReaderQuery": "DECLARE @RETURN_VALUE_ARGUMENT DECIMAL\nEXECUTE [dbo].[GET_NEW_LOADID]\n@RETURN_VALUE_ARGUMENT OUTPUT\n,@P_DATA_LOCATION_NAME = 'Retail_ProductMaster'\n,@P_PROGRAM_NAME = 'ProductMasterLoad'\n,@P_LOAD_DESCRIPTION = 'ProductMasterLoad'\n,@P_USERNAME = 'semadmin'\nSELECT @RETURN_VALUE_ARGUMENT AS RETURN_VALUE_ARGUMENT",
						"queryTimeout": "02:00:00",
						"partitionOption": "None"
					},
					"dataset": {
						"referenceName": "Semarchy_Repo",
						"type": "DatasetReference"
					}
				}
			},
			{
				"name": "SetNewLoadId",
				"type": "SetVariable",
				"dependsOn": [
					{
						"activity": "GetNewLoadId",
						"dependencyConditions": [
							"Succeeded"
						]
					}
				],
				"policy": {
					"secureOutput": false,
					"secureInput": false
				},
				"userProperties": [],
				"typeProperties": {
					"variableName": "LoadID",
					"value": {
						"value": "@{activity('GetNewLoadId').output.firstRow.RETURN_VALUE_ARGUMENT}",
						"type": "Expression"
					}
				}
			},
			{
				"name": "Load_Retail_PIM_Delete_EDWProduct",
				"type": "Copy",
				"dependsOn": [
					{
						"activity": "SetDateVariables",
						"dependencyConditions": [
							"Succeeded"
						]
					}
				],
				"policy": {
					"timeout": "0.12:00:00",
					"retry": 0,
					"retryIntervalInSeconds": 30,
					"secureOutput": false,
					"secureInput": false
				},
				"userProperties": [],
				"typeProperties": {
					"source": {
						"type": "AzureSqlSource",
						"additionalColumns": [
							{
								"name": "LoadID",
								"value": {
									"value": "@variables('LoadID')",
									"type": "Expression"
								}
							}
						],
						"sqlReaderQuery": {
							"value": "SELECT\nGETDATE() AS B_CREDATE,\n'ProductMain' AS B_CLASSNAME,\nSUBSTRING(id, 1, CASE WHEN CHARINDEX('_', id, 1)=0 THEN LEN(id) ELSE CHARINDEX('_', id, 1)- 1 END ) \nAS PRODUCT_MAIN_ID,\n'SOFT_DELETE' AS B_DELETETYPE,\nnewID() AS B_DELETEOPERATION,\n'semadmin' AS B_DELETEAUTHOR,\nGETDATE() AS B_DELETEDATE\nFROM [Retail].[EDWProduct] WITH(NOLOCK) WHERE Status='Deleted' AND WHERE CAST(LastModifiedDateTimeUtc as date)>='@{variables('Date')}' AND SUBSTRING(id, 1, CASE WHEN CHARINDEX('_', id, 1)=0 THEN LEN(id) ELSE CHARINDEX('_', id, 1)- 1 END )='D698-25T'",
							"type": "Expression"
						},
						"queryTimeout": "02:00:00",
						"partitionOption": "None"
					},
					"sink": {
						"type": "AzureSqlSink",
						"writeBehavior": "insert",
						"sqlWriterUseTableLock": false,
						"disableMetricsCollection": false
					},
					"enableStaging": false,
					"dataIntegrationUnits": 2,
					"translator": {
						"type": "TabularTranslator",
						"mappings": [
							{
								"source": {
									"name": "LoadID",
									"type": "String"
								},
								"sink": {
									"name": "B_LOADID",
									"type": "Decimal",
									"physicalType": "decimal",
									"scale": 0,
									"precision": 38
								}
							},
							{
								"source": {
									"name": "PRODUCT_MAIN_ID",
									"type": "String",
									"physicalType": "varchar"
								},
								"sink": {
									"name": "PRODUCT_MAIN_ID",
									"type": "String",
									"physicalType": "nvarchar"
								}
							},
							{
								"source": {
									"name": "B_CLASSNAME",
									"type": "String",
									"physicalType": "varchar"
								},
								"sink": {
									"name": "B_CLASSNAME",
									"type": "String",
									"physicalType": "nvarchar"
								}
							},
							{
								"source": {
									"name": "B_DELETETYPE",
									"type": "String",
									"physicalType": "varchar"
								},
								"sink": {
									"name": "B_DELETETYPE",
									"type": "String",
									"physicalType": "nvarchar"
								}
							},
							{
								"source": {
									"name": "B_DELETEDATE",
									"type": "DateTime",
									"physicalType": "datetime"
								},
								"sink": {
									"name": "B_DELETEDATE",
									"type": "DateTime",
									"physicalType": "datetime2"
								}
							},
							{
								"source": {
									"name": "B_DELETEAUTHOR",
									"type": "String",
									"physicalType": "varchar"
								},
								"sink": {
									"name": "B_DELETEAUTHOR",
									"type": "String",
									"physicalType": "nvarchar"
								}
							},
							{
								"source": {
									"name": "B_DELETEOPERATION",
									"type": "Guid",
									"physicalType": "uniqueidentifier"
								},
								"sink": {
									"name": "B_DELETEOPERATION",
									"type": "String",
									"physicalType": "nvarchar"
								}
							},
							{
								"source": {
									"name": "B_CREDATE",
									"type": "DateTime",
									"physicalType": "datetime"
								},
								"sink": {
									"name": "B_CREDATE",
									"type": "DateTime",
									"physicalType": "datetime2"
								}
							}
						],
						"typeConversion": true,
						"typeConversionSettings": {
							"allowDataTruncation": true,
							"treatBooleanAsNumber": false
						}
					}
				},
				"inputs": [
					{
						"referenceName": "Semarchy_Staging",
						"type": "DatasetReference"
					}
				],
				"outputs": [
					{
						"referenceName": "Retail_ProductMaster_EDW_Product",
						"type": "DatasetReference"
					}
				]
			},
			{
				"name": "Load_Retail_PIM_Delete_EDWProductKit",
				"type": "Copy",
				"dependsOn": [
					{
						"activity": "Load_Retail_PIM_Delete_EDWProduct",
						"dependencyConditions": [
							"Succeeded"
						]
					}
				],
				"policy": {
					"timeout": "0.12:00:00",
					"retry": 0,
					"retryIntervalInSeconds": 30,
					"secureOutput": false,
					"secureInput": false
				},
				"userProperties": [],
				"typeProperties": {
					"source": {
						"type": "AzureSqlSource",
						"additionalColumns": [
							{
								"name": "LoadID",
								"value": {
									"value": "@variables('LoadID')",
									"type": "Expression"
								}
							}
						],
						"sqlReaderQuery": {
							"value": "SELECT\nGETDATE() AS B_CREDATE,\n'ProductKit' AS B_CLASSNAME,\nSUBSTRING(KitID, 1, CASE WHEN CHARINDEX('_', KitID, 1)=0 THEN LEN(KitID) ELSE CHARINDEX('_', KitID, 1)- 1 END )\nAS KIT_ID,\n'SOFT_DELETE' AS B_DELETETYPE,\nnewID() AS B_DELETEOPERATION,\n'semadmin' AS B_DELETEAUTHOR,\nGETDATE() AS B_DELETEDATE\nFROM [Retail].[EDWProductKit] WITH(NOLOCK) WHERE KitStatus='Deleted' AND CAST(LastModifiedDateTimeUtc as date)>='@{variables('Date')}' AND SUBSTRING(KitID, 1, CASE WHEN CHARINDEX('_', KitID, 1)=0 THEN LEN(KitID) ELSE CHARINDEX('_', KitID, 1)- 1 END )='B617B5'",
							"type": "Expression"
						},
						"queryTimeout": "02:00:00",
						"partitionOption": "None"
					},
					"sink": {
						"type": "AzureSqlSink",
						"writeBehavior": "insert",
						"sqlWriterUseTableLock": false,
						"disableMetricsCollection": false
					},
					"enableStaging": false,
					"dataIntegrationUnits": 2,
					"translator": {
						"type": "TabularTranslator",
						"mappings": [
							{
								"source": {
									"name": "LoadID",
									"type": "String"
								},
								"sink": {
									"name": "B_LOADID",
									"type": "Decimal",
									"physicalType": "decimal",
									"scale": 0,
									"precision": 38
								}
							},
							{
								"source": {
									"name": "KIT_ID",
									"type": "String",
									"physicalType": "varchar"
								},
								"sink": {
									"name": "KIT_ID",
									"type": "String",
									"physicalType": "nvarchar"
								}
							},
							{
								"source": {
									"name": "B_CLASSNAME",
									"type": "String",
									"physicalType": "varchar"
								},
								"sink": {
									"name": "B_CLASSNAME",
									"type": "String",
									"physicalType": "nvarchar"
								}
							},
							{
								"source": {
									"name": "B_DELETETYPE",
									"type": "String",
									"physicalType": "varchar"
								},
								"sink": {
									"name": "B_DELETETYPE",
									"type": "String",
									"physicalType": "nvarchar"
								}
							},
							{
								"source": {
									"name": "B_DELETEDATE",
									"type": "DateTime",
									"physicalType": "datetime"
								},
								"sink": {
									"name": "B_DELETEDATE",
									"type": "DateTime",
									"physicalType": "datetime2"
								}
							},
							{
								"source": {
									"name": "B_DELETEAUTHOR",
									"type": "String",
									"physicalType": "varchar"
								},
								"sink": {
									"name": "B_DELETEAUTHOR",
									"type": "String",
									"physicalType": "nvarchar"
								}
							},
							{
								"source": {
									"name": "B_DELETEOPERATION",
									"type": "Guid",
									"physicalType": "uniqueidentifier"
								},
								"sink": {
									"name": "B_DELETEOPERATION",
									"type": "String",
									"physicalType": "nvarchar"
								}
							},
							{
								"source": {
									"name": "B_CREDATE",
									"type": "DateTime",
									"physicalType": "datetime"
								},
								"sink": {
									"name": "B_CREDATE",
									"type": "DateTime",
									"physicalType": "datetime2"
								}
							}
						],
						"typeConversion": true,
						"typeConversionSettings": {
							"allowDataTruncation": true,
							"treatBooleanAsNumber": false
						}
					}
				},
				"inputs": [
					{
						"referenceName": "Semarchy_Staging",
						"type": "DatasetReference"
					}
				],
				"outputs": [
					{
						"referenceName": "Retail_ProductMaster_EDW_ProductKit",
						"type": "DatasetReference"
					}
				]
			},
			{
				"name": "Load_Retail_PIM_Delete_EDWProductPackage",
				"type": "Copy",
				"dependsOn": [
					{
						"activity": "Load_Retail_PIM_Delete_EDWProductKit",
						"dependencyConditions": [
							"Succeeded"
						]
					}
				],
				"policy": {
					"timeout": "0.12:00:00",
					"retry": 0,
					"retryIntervalInSeconds": 30,
					"secureOutput": false,
					"secureInput": false
				},
				"userProperties": [],
				"typeProperties": {
					"source": {
						"type": "AzureSqlSource",
						"additionalColumns": [
							{
								"name": "LoadID",
								"value": {
									"value": "@variables('LoadID')",
									"type": "Expression"
								}
							}
						],
						"sqlReaderQuery": {
							"value": "SELECT\nGETDATE() AS B_CREDATE,\n'ProductPackage' AS B_CLASSNAME,\nSUBSTRING(PackageID, 1, CASE WHEN CHARINDEX('_', PackageID, 1)=0 THEN LEN(PackageID) ELSE CHARINDEX('_', PackageID, 1)- 1 END )\nAS PACKAGE_ID,\n'SOFT_DELETE' AS B_DELETETYPE,\nnewID() AS B_DELETEOPERATION,\n'semadmin' AS B_DELETEAUTHOR,\nGETDATE() AS B_DELETEDATE\nFROM [Retail].[EDWProductPackage] WITH(NOLOCK) WHERE PackageStatus='Deleted' AND CAST(LastModifiedDateTimeUtc as date)>='@{variables('Date')}' AND \nSUBSTRING(PackageID, 1, CASE WHEN CHARINDEX('_', PackageID, 1)=0 THEN LEN(PackageID) ELSE CHARINDEX('_', PackageID, 1)- 1 END )='PKG013419'\n",
							"type": "Expression"
						},
						"queryTimeout": "02:00:00",
						"partitionOption": "None"
					},
					"sink": {
						"type": "AzureSqlSink",
						"writeBehavior": "insert",
						"sqlWriterUseTableLock": false,
						"disableMetricsCollection": false
					},
					"enableStaging": false,
					"dataIntegrationUnits": 2,
					"translator": {
						"type": "TabularTranslator",
						"mappings": [
							{
								"source": {
									"name": "LoadID",
									"type": "String"
								},
								"sink": {
									"name": "B_LOADID",
									"type": "Decimal",
									"physicalType": "decimal",
									"scale": 0,
									"precision": 38
								}
							},
							{
								"source": {
									"name": "PACKAGE_ID",
									"type": "String",
									"physicalType": "varchar"
								},
								"sink": {
									"name": "PACKAGE_ID",
									"type": "String",
									"physicalType": "nvarchar"
								}
							},
							{
								"source": {
									"name": "B_CLASSNAME",
									"type": "String",
									"physicalType": "varchar"
								},
								"sink": {
									"name": "B_CLASSNAME",
									"type": "String",
									"physicalType": "nvarchar"
								}
							},
							{
								"source": {
									"name": "B_DELETETYPE",
									"type": "String",
									"physicalType": "varchar"
								},
								"sink": {
									"name": "B_DELETETYPE",
									"type": "String",
									"physicalType": "nvarchar"
								}
							},
							{
								"source": {
									"name": "B_DELETEDATE",
									"type": "DateTime",
									"physicalType": "datetime"
								},
								"sink": {
									"name": "B_DELETEDATE",
									"type": "DateTime",
									"physicalType": "datetime2"
								}
							},
							{
								"source": {
									"name": "B_DELETEAUTHOR",
									"type": "String",
									"physicalType": "varchar"
								},
								"sink": {
									"name": "B_DELETEAUTHOR",
									"type": "String",
									"physicalType": "nvarchar"
								}
							},
							{
								"source": {
									"name": "B_DELETEOPERATION",
									"type": "Guid",
									"physicalType": "uniqueidentifier"
								},
								"sink": {
									"name": "B_DELETEOPERATION",
									"type": "String",
									"physicalType": "nvarchar"
								}
							},
							{
								"source": {
									"name": "B_CREDATE",
									"type": "DateTime",
									"physicalType": "datetime"
								},
								"sink": {
									"name": "B_CREDATE",
									"type": "DateTime",
									"physicalType": "datetime2"
								}
							}
						],
						"typeConversion": true,
						"typeConversionSettings": {
							"allowDataTruncation": true,
							"treatBooleanAsNumber": false
						}
					}
				},
				"inputs": [
					{
						"referenceName": "Semarchy_Staging",
						"type": "DatasetReference"
					}
				],
				"outputs": [
					{
						"referenceName": "Retail_ProductMaster_EDW_ProductPackage",
						"type": "DatasetReference"
					}
				]
			},
			{
				"name": "SubmitLoadID",
				"type": "SqlServerStoredProcedure",
				"dependsOn": [
					{
						"activity": "Load_Retail_PIM_Delete_EDWProductPackage",
						"dependencyConditions": [
							"Succeeded"
						]
					}
				],
				"policy": {
					"timeout": "0.12:00:00",
					"retry": 0,
					"retryIntervalInSeconds": 30,
					"secureOutput": false,
					"secureInput": false
				},
				"userProperties": [],
				"typeProperties": {
					"storedProcedureName": "[dbo].[SUBMIT_LOAD]",
					"storedProcedureParameters": {
						"P_INTEGRATION_JOB_NAME": {
							"value": {
								"value": "ProductMasterLoad",
								"type": "Expression"
							},
							"type": "String"
						},
						"P_LOAD_ID": {
							"value": {
								"value": "@variables('LoadID')",
								"type": "Expression"
							},
							"type": "Decimal"
						},
						"P_USERNAME": {
							"value": {
								"value": "semadmin",
								"type": "Expression"
							},
							"type": "String"
						},
						"return_value_argument": {
							"value": null,
							"type": "Decimal"
						}
					}
				},
				"linkedServiceName": {
					"referenceName": "semarchy_repo",
					"type": "LinkedServiceReference"
				}
			},
			{
				"name": "SetDateVariables",
				"type": "SetVariable",
				"dependsOn": [
					{
						"activity": "SetNewLoadId",
						"dependencyConditions": [
							"Succeeded"
						]
					}
				],
				"policy": {
					"secureOutput": false,
					"secureInput": false
				},
				"userProperties": [],
				"typeProperties": {
					"variableName": "Date",
					"value": {
						"value": "@formatDateTime(adddays(startOfDay(utcnow()),-1), 'yyyy-MM-dd')",
						"type": "Expression"
					}
				}
			},
			{
				"name": "Product_ErrorLoags",
				"type": "SqlServerStoredProcedure",
				"dependsOn": [
					{
						"activity": "Load_Retail_PIM_Delete_EDWProduct",
						"dependencyConditions": [
							"Failed"
						]
					}
				],
				"policy": {
					"timeout": "0.12:00:00",
					"retry": 0,
					"retryIntervalInSeconds": 30,
					"secureOutput": false,
					"secureInput": false
				},
				"userProperties": [],
				"typeProperties": {
					"storedProcedureName": "[Audit].[uspInsertADFErrorLog]",
					"storedProcedureParameters": {
						"ErrorCode": {
							"value": {
								"value": "@{activity('Load_Retail_PIM_Delete_EDWProduct').error.errorCode}",
								"type": "Expression"
							},
							"type": "String"
						},
						"ErrorMsg": {
							"value": {
								"value": "@{activity('Load_Retail_PIM_Delete_EDWProduct').error.message}",
								"type": "Expression"
							},
							"type": "String"
						},
						"ErrorStatusCode": {
							"value": {
								"value": "@activity('Load_Retail_PIM_Delete_EDWProduct').StatusCode",
								"type": "Expression"
							},
							"type": "String"
						},
						"FailureType": {
							"value": {
								"value": "@{activity('Load_Retail_PIM_Delete_EDWProduct').error.failureType}",
								"type": "Expression"
							},
							"type": "String"
						},
						"PipelineName": {
							"value": {
								"value": "@{pipeline().Pipeline}",
								"type": "Expression"
							},
							"type": "String"
						},
						"RunID": {
							"value": {
								"value": "@{pipeline().RunId}",
								"type": "Expression"
							},
							"type": "String"
						},
						"Sink": {
							"value": {
								"value": "dbo.SA_PRODUCT_MAIN",
								"type": "Expression"
							},
							"type": "String"
						},
						"Sink_Type": {
							"value": {
								"value": "@{activity('Load_Retail_PIM_Delete_EDWProduct').output.executionDetails[0].sink.type}",
								"type": "Expression"
							},
							"type": "String"
						},
						"Source": {
							"value": {
								"value": "[Retail].[EDWProduct]",
								"type": "Expression"
							},
							"type": "String"
						},
						"Source_Type": {
							"value": {
								"value": "@{activity('Load_Retail_PIM_Delete_EDWProduct').output.executionDetails[0].source.type}",
								"type": "Expression"
							},
							"type": "String"
						},
						"TriggerId": {
							"value": {
								"value": "@{pipeline().TriggerId}",
								"type": "Expression"
							},
							"type": "String"
						},
						"TriggerName": {
							"value": {
								"value": "@{pipeline().TriggerName}",
								"type": "Expression"
							},
							"type": "String"
						},
						"TriggerTime": {
							"value": {
								"value": "@{pipeline().TriggerTime}",
								"type": "Expression"
							},
							"type": "String"
						},
						"TriggerType": {
							"value": {
								"value": "@{pipeline().TriggerType}",
								"type": "Expression"
							},
							"type": "String"
						}
					}
				},
				"linkedServiceName": {
					"referenceName": "semarchy_staging",
					"type": "LinkedServiceReference"
				}
			},
			{
				"name": "Teams_Failed_Notification_Product",
				"type": "ExecutePipeline",
				"dependsOn": [
					{
						"activity": "Load_Retail_PIM_Delete_EDWProduct",
						"dependencyConditions": [
							"Failed"
						]
					}
				],
				"userProperties": [],
				"typeProperties": {
					"pipeline": {
						"referenceName": "Notify_Teams_Channale_Pipeline",
						"type": "PipelineReference"
					},
					"waitOnCompletion": true,
					"parameters": {
						"subscription": {
							"value": "@pipeline().globalParameters.ADF_SubscriptionID",
							"type": "Expression"
						},
						"resourceGroup": "afi-edme-rg",
						"runId": {
							"value": "@pipeline().RunId",
							"type": "Expression"
						},
						"name": {
							"value": "@pipeline().Pipeline",
							"type": "Expression"
						},
						"triggerTime": {
							"value": "@activity('Load_Retail_PIM_Delete_EDWProduct').output.executionDetails[0].start",
							"type": "Expression"
						},
						"status": {
							"value": "@activity('Load_Retail_PIM_Delete_EDWProduct').output.executionDetails[0].status",
							"type": "Expression"
						},
						"message": {
							"value": "@replace(activity('Load_Retail_PIM_Delete_EDWProduct').error.message,'\"','')",
							"type": "Expression"
						},
						"executionEndTime": {
							"value": "@{utcnow()}",
							"type": "Expression"
						},
						"runDuration": {
							"value": "@activity('Load_Retail_PIM_Delete_EDWProduct').output.copyDuration",
							"type": "Expression"
						},
						"teamWebhookUrl": {
							"value": "https://masterashley.webhook.office.com/webhookb2/c31879ef-6dfb-470f-b788-de8363ae3c17@5a9d9cfd-c32e-4ac1-a9ed-fe83df4f9e4d/IncomingWebhook/147e6de5d4454f53bc64a6a9bae90283/276c88be-8000-43f8-b798-97215f5a2fda",
							"type": "Expression"
						}
					}
				}
			},
			{
				"name": "Product_SuccessLogging",
				"type": "SqlServerStoredProcedure",
				"dependsOn": [
					{
						"activity": "Load_Retail_PIM_Delete_EDWProduct",
						"dependencyConditions": [
							"Succeeded"
						]
					}
				],
				"policy": {
					"timeout": "0.12:00:00",
					"retry": 0,
					"retryIntervalInSeconds": 30,
					"secureOutput": false,
					"secureInput": false
				},
				"userProperties": [],
				"typeProperties": {
					"storedProcedureName": "[Audit].[uspInsertADFLogging]",
					"storedProcedureParameters": {
						"CopyActivity_End_Time": {
							"value": {
								"value": "@{utcnow()}",
								"type": "Expression"
							},
							"type": "DateTime"
						},
						"CopyActivity_Start_Time": {
							"value": {
								"value": "@{activity('Load_Retail_PIM_Delete_EDWProduct').output.executionDetails[0].start}",
								"type": "Expression"
							},
							"type": "DateTime"
						},
						"CopyActivity_transferDuration_in_secs": {
							"value": {
								"value": "@{activity('Load_Retail_PIM_Delete_EDWProduct').output.executionDetails[0]. detailedDurations.transferDuration}",
								"type": "Expression"
							},
							"type": "Int32"
						},
						"CopyDuration_in_secs": {
							"value": {
								"value": "@{activity('Load_Retail_PIM_Delete_EDWProduct').output.copyDuration}",
								"type": "Expression"
							},
							"type": "Int32"
						},
						"Execution_Status": {
							"value": {
								"value": "@{activity('Load_Retail_PIM_Delete_EDWProduct').output.executionDetails[0].status}",
								"type": "Expression"
							},
							"type": "String"
						},
						"Pipeline_Name": {
							"value": {
								"value": "@{pipeline().Pipeline}",
								"type": "Expression"
							},
							"type": "String"
						},
						"RowsCopied": {
							"value": {
								"value": "@{activity('Load_Retail_PIM_Delete_EDWProduct').output.rowsCopied}",
								"type": "Expression"
							},
							"type": "Int32"
						},
						"RowsRead": {
							"value": {
								"value": "@{activity('Load_Retail_PIM_Delete_EDWProduct').output.rowsRead}",
								"type": "Expression"
							},
							"type": "Int32"
						},
						"RunId": {
							"value": {
								"value": "@{pipeline().RunId}",
								"type": "Expression"
							},
							"type": "String"
						},
						"Sink": {
							"value": {
								"value": "dbo.SA_PRODUCT_MAIN",
								"type": "Expression"
							},
							"type": "String"
						},
						"Sink_Type": {
							"value": {
								"value": "@{activity('Load_Retail_PIM_Delete_EDWProduct').output.executionDetails[0].sink.type}",
								"type": "Expression"
							},
							"type": "String"
						},
						"Source": {
							"value": {
								"value": "[Retail].[EDWProduct]",
								"type": "Expression"
							},
							"type": "String"
						},
						"Source_Type": {
							"value": {
								"value": "@{activity('Load_Retail_PIM_Delete_EDWProduct').output.executionDetails[0].source.type}",
								"type": "Expression"
							},
							"type": "String"
						},
						"TriggerId": {
							"value": {
								"value": "@{pipeline().TriggerId}",
								"type": "Expression"
							},
							"type": "String"
						},
						"TriggerName": {
							"value": {
								"value": "@{pipeline().TriggerName}",
								"type": "Expression"
							},
							"type": "String"
						},
						"TriggerTime": {
							"value": {
								"value": "@{pipeline().TriggerTime}",
								"type": "Expression"
							},
							"type": "DateTime"
						},
						"TriggerType": {
							"value": {
								"value": "@{pipeline().TriggerType}",
								"type": "Expression"
							},
							"type": "String"
						}
					}
				},
				"linkedServiceName": {
					"referenceName": "semarchy_staging",
					"type": "LinkedServiceReference"
				}
			},
			{
				"name": "ProductKit_ErrorLoags",
				"type": "SqlServerStoredProcedure",
				"dependsOn": [
					{
						"activity": "Load_Retail_PIM_Delete_EDWProductKit",
						"dependencyConditions": [
							"Failed"
						]
					}
				],
				"policy": {
					"timeout": "0.12:00:00",
					"retry": 0,
					"retryIntervalInSeconds": 30,
					"secureOutput": false,
					"secureInput": false
				},
				"userProperties": [],
				"typeProperties": {
					"storedProcedureName": "[Audit].[uspInsertADFErrorLog]",
					"storedProcedureParameters": {
						"ErrorCode": {
							"value": {
								"value": "@{activity('Load_Retail_PIM_Delete_EDWProductKit').error.errorCode}",
								"type": "Expression"
							},
							"type": "String"
						},
						"ErrorMsg": {
							"value": {
								"value": "@{activity('Load_Retail_PIM_Delete_EDWProductKit').error.message}",
								"type": "Expression"
							},
							"type": "String"
						},
						"ErrorStatusCode": {
							"value": {
								"value": "@activity('Load_Retail_PIM_Delete_EDWProductKit').StatusCode",
								"type": "Expression"
							},
							"type": "String"
						},
						"FailureType": {
							"value": {
								"value": "@{activity('Load_Retail_PIM_Delete_EDWProductKit').error.failureType}",
								"type": "Expression"
							},
							"type": "String"
						},
						"PipelineName": {
							"value": {
								"value": "@{pipeline().Pipeline}",
								"type": "Expression"
							},
							"type": "String"
						},
						"RunID": {
							"value": {
								"value": "@{pipeline().RunId}",
								"type": "Expression"
							},
							"type": "String"
						},
						"Sink": {
							"value": {
								"value": "dbo.SA_PRODUCT_KIT",
								"type": "Expression"
							},
							"type": "String"
						},
						"Sink_Type": {
							"value": {
								"value": "@{activity('Load_Retail_PIM_Delete_EDWProductKit').output.executionDetails[0].sink.type}",
								"type": "Expression"
							},
							"type": "String"
						},
						"Source": {
							"value": {
								"value": "[Retail].[EDWProductKit]",
								"type": "Expression"
							},
							"type": "String"
						},
						"Source_Type": {
							"value": {
								"value": "@{activity('Load_Retail_PIM_Delete_EDWProductKit').output.executionDetails[0].source.type}",
								"type": "Expression"
							},
							"type": "String"
						},
						"TriggerId": {
							"value": {
								"value": "@{pipeline().TriggerId}",
								"type": "Expression"
							},
							"type": "String"
						},
						"TriggerName": {
							"value": {
								"value": "@{pipeline().TriggerName}",
								"type": "Expression"
							},
							"type": "String"
						},
						"TriggerTime": {
							"value": {
								"value": "@{pipeline().TriggerTime}",
								"type": "Expression"
							},
							"type": "String"
						},
						"TriggerType": {
							"value": {
								"value": "@{pipeline().TriggerType}",
								"type": "Expression"
							},
							"type": "String"
						}
					}
				},
				"linkedServiceName": {
					"referenceName": "semarchy_staging",
					"type": "LinkedServiceReference"
				}
			},
			{
				"name": "Teams_Failed_Notification_ProductKit",
				"type": "ExecutePipeline",
				"dependsOn": [
					{
						"activity": "Load_Retail_PIM_Delete_EDWProductKit",
						"dependencyConditions": [
							"Failed"
						]
					}
				],
				"userProperties": [],
				"typeProperties": {
					"pipeline": {
						"referenceName": "Notify_Teams_Channale_Pipeline",
						"type": "PipelineReference"
					},
					"waitOnCompletion": true,
					"parameters": {
						"subscription": {
							"value": "@pipeline().globalParameters.ADF_SubscriptionID",
							"type": "Expression"
						},
						"resourceGroup": "afi-edme-rg",
						"runId": {
							"value": "@pipeline().RunId",
							"type": "Expression"
						},
						"name": {
							"value": "@pipeline().Pipeline",
							"type": "Expression"
						},
						"triggerTime": {
							"value": "@activity('Load_Retail_PIM_Delete_EDWProductKit').output.executionDetails[0].start",
							"type": "Expression"
						},
						"status": {
							"value": "@activity('Load_Retail_PIM_Delete_EDWProductKit').output.executionDetails[0].status",
							"type": "Expression"
						},
						"message": {
							"value": "@replace(activity('Load_Retail_PIM_Delete_EDWProductKit').error.message,'\"','')",
							"type": "Expression"
						},
						"executionEndTime": {
							"value": "@{utcnow()}",
							"type": "Expression"
						},
						"runDuration": {
							"value": "@activity('Load_Retail_PIM_Delete_EDWProductKit').output.copyDuration",
							"type": "Expression"
						},
						"teamWebhookUrl": {
							"value": "https://masterashley.webhook.office.com/webhookb2/c31879ef-6dfb-470f-b788-de8363ae3c17@5a9d9cfd-c32e-4ac1-a9ed-fe83df4f9e4d/IncomingWebhook/147e6de5d4454f53bc64a6a9bae90283/276c88be-8000-43f8-b798-97215f5a2fda",
							"type": "Expression"
						}
					}
				}
			},
			{
				"name": "ProductKit_SuccessLogging",
				"type": "SqlServerStoredProcedure",
				"dependsOn": [
					{
						"activity": "Load_Retail_PIM_Delete_EDWProductKit",
						"dependencyConditions": [
							"Succeeded"
						]
					}
				],
				"policy": {
					"timeout": "0.12:00:00",
					"retry": 0,
					"retryIntervalInSeconds": 30,
					"secureOutput": false,
					"secureInput": false
				},
				"userProperties": [],
				"typeProperties": {
					"storedProcedureName": "[Audit].[uspInsertADFLogging]",
					"storedProcedureParameters": {
						"CopyActivity_End_Time": {
							"value": {
								"value": "@{utcnow()}",
								"type": "Expression"
							},
							"type": "DateTime"
						},
						"CopyActivity_Start_Time": {
							"value": {
								"value": "@{activity('Load_Retail_PIM_Delete_EDWProductKit').output.executionDetails[0].start}",
								"type": "Expression"
							},
							"type": "DateTime"
						},
						"CopyActivity_transferDuration_in_secs": {
							"value": {
								"value": "@{activity('Load_Retail_PIM_Delete_EDWProductKit').output.executionDetails[0]. detailedDurations.transferDuration}",
								"type": "Expression"
							},
							"type": "Int32"
						},
						"CopyDuration_in_secs": {
							"value": {
								"value": "@{activity('Load_Retail_PIM_Delete_EDWProductKit').output.copyDuration}",
								"type": "Expression"
							},
							"type": "Int32"
						},
						"Execution_Status": {
							"value": {
								"value": "@{activity('Load_Retail_PIM_Delete_EDWProductKit').output.executionDetails[0].status}",
								"type": "Expression"
							},
							"type": "String"
						},
						"Pipeline_Name": {
							"value": {
								"value": "@{pipeline().Pipeline}",
								"type": "Expression"
							},
							"type": "String"
						},
						"RowsCopied": {
							"value": {
								"value": "@{activity('Load_Retail_PIM_Delete_EDWProductKit').output.rowsCopied}",
								"type": "Expression"
							},
							"type": "Int32"
						},
						"RowsRead": {
							"value": {
								"value": "@{activity('Load_Retail_PIM_Delete_EDWProductKit').output.rowsRead}",
								"type": "Expression"
							},
							"type": "Int32"
						},
						"RunId": {
							"value": {
								"value": "@{pipeline().RunId}",
								"type": "Expression"
							},
							"type": "String"
						},
						"Sink": {
							"value": {
								"value": "dbo.SA_PRODUCT_KIT",
								"type": "Expression"
							},
							"type": "String"
						},
						"Sink_Type": {
							"value": {
								"value": "@{activity('Load_Retail_PIM_Delete_EDWProductKit').output.executionDetails[0].sink.type}",
								"type": "Expression"
							},
							"type": "String"
						},
						"Source": {
							"value": {
								"value": "[Retail].[EDWProductKit]",
								"type": "Expression"
							},
							"type": "String"
						},
						"Source_Type": {
							"value": {
								"value": "@{activity('Load_Retail_PIM_Delete_EDWProductKit').output.executionDetails[0].source.type}",
								"type": "Expression"
							},
							"type": "String"
						},
						"TriggerId": {
							"value": {
								"value": "@{pipeline().TriggerId}",
								"type": "Expression"
							},
							"type": "String"
						},
						"TriggerName": {
							"value": {
								"value": "@{pipeline().TriggerName}",
								"type": "Expression"
							},
							"type": "String"
						},
						"TriggerTime": {
							"value": {
								"value": "@{pipeline().TriggerTime}",
								"type": "Expression"
							},
							"type": "DateTime"
						},
						"TriggerType": {
							"value": {
								"value": "@{pipeline().TriggerType}",
								"type": "Expression"
							},
							"type": "String"
						}
					}
				},
				"linkedServiceName": {
					"referenceName": "semarchy_staging",
					"type": "LinkedServiceReference"
				}
			},
			{
				"name": "ProductPackage_ErrorLoags",
				"type": "SqlServerStoredProcedure",
				"dependsOn": [
					{
						"activity": "Load_Retail_PIM_Delete_EDWProductPackage",
						"dependencyConditions": [
							"Failed"
						]
					}
				],
				"policy": {
					"timeout": "0.12:00:00",
					"retry": 0,
					"retryIntervalInSeconds": 30,
					"secureOutput": false,
					"secureInput": false
				},
				"userProperties": [],
				"typeProperties": {
					"storedProcedureName": "[Audit].[uspInsertADFErrorLog]",
					"storedProcedureParameters": {
						"ErrorCode": {
							"value": {
								"value": "@{activity('Load_Retail_PIM_Delete_EDWProductPackage').error.errorCode}",
								"type": "Expression"
							},
							"type": "String"
						},
						"ErrorMsg": {
							"value": {
								"value": "@{activity('Load_Retail_PIM_Delete_EDWProductPackage').error.message}",
								"type": "Expression"
							},
							"type": "String"
						},
						"ErrorStatusCode": {
							"value": {
								"value": "@activity('Load_Retail_PIM_Delete_EDWProductPackage').StatusCode",
								"type": "Expression"
							},
							"type": "String"
						},
						"FailureType": {
							"value": {
								"value": "@{activity('Load_Retail_PIM_Delete_EDWProductPackage').error.failureType}",
								"type": "Expression"
							},
							"type": "String"
						},
						"PipelineName": {
							"value": {
								"value": "@{pipeline().Pipeline}",
								"type": "Expression"
							},
							"type": "String"
						},
						"RunID": {
							"value": {
								"value": "@{pipeline().RunId}",
								"type": "Expression"
							},
							"type": "String"
						},
						"Sink": {
							"value": {
								"value": "dbo.SA_PRODUCT_PACKAGE",
								"type": "Expression"
							},
							"type": "String"
						},
						"Sink_Type": {
							"value": {
								"value": "@{activity('Load_Retail_PIM_Delete_EDWProductPackage').output.executionDetails[0].sink.type}",
								"type": "Expression"
							},
							"type": "String"
						},
						"Source": {
							"value": {
								"value": "[Retail].[EDWProductPackage]",
								"type": "Expression"
							},
							"type": "String"
						},
						"Source_Type": {
							"value": {
								"value": "@{activity('Load_Retail_PIM_Delete_EDWProductPackage').output.executionDetails[0].source.type}",
								"type": "Expression"
							},
							"type": "String"
						},
						"TriggerId": {
							"value": {
								"value": "@{pipeline().TriggerId}",
								"type": "Expression"
							},
							"type": "String"
						},
						"TriggerName": {
							"value": {
								"value": "@{pipeline().TriggerName}",
								"type": "Expression"
							},
							"type": "String"
						},
						"TriggerTime": {
							"value": {
								"value": "@{pipeline().TriggerTime}",
								"type": "Expression"
							},
							"type": "String"
						},
						"TriggerType": {
							"value": {
								"value": "@{pipeline().TriggerType}",
								"type": "Expression"
							},
							"type": "String"
						}
					}
				},
				"linkedServiceName": {
					"referenceName": "semarchy_staging",
					"type": "LinkedServiceReference"
				}
			},
			{
				"name": "ProductPackage_SuccessLogging",
				"type": "SqlServerStoredProcedure",
				"dependsOn": [
					{
						"activity": "Load_Retail_PIM_Delete_EDWProductPackage",
						"dependencyConditions": [
							"Succeeded"
						]
					}
				],
				"policy": {
					"timeout": "0.12:00:00",
					"retry": 0,
					"retryIntervalInSeconds": 30,
					"secureOutput": false,
					"secureInput": false
				},
				"userProperties": [],
				"typeProperties": {
					"storedProcedureName": "[Audit].[uspInsertADFLogging]",
					"storedProcedureParameters": {
						"CopyActivity_End_Time": {
							"value": {
								"value": "@{utcnow()}",
								"type": "Expression"
							},
							"type": "DateTime"
						},
						"CopyActivity_Start_Time": {
							"value": {
								"value": "@{activity('Load_Retail_PIM_Delete_EDWProductPackage').output.executionDetails[0].start}",
								"type": "Expression"
							},
							"type": "DateTime"
						},
						"CopyActivity_transferDuration_in_secs": {
							"value": {
								"value": "@{activity('Load_Retail_PIM_Delete_EDWProductPackage').output.executionDetails[0]. detailedDurations.transferDuration}",
								"type": "Expression"
							},
							"type": "Int32"
						},
						"CopyDuration_in_secs": {
							"value": {
								"value": "@{activity('Load_Retail_PIM_Delete_EDWProductPackage').output.copyDuration}",
								"type": "Expression"
							},
							"type": "Int32"
						},
						"Execution_Status": {
							"value": {
								"value": "@{activity('Load_Retail_PIM_Delete_EDWProductPackage').output.executionDetails[0].status}",
								"type": "Expression"
							},
							"type": "String"
						},
						"Pipeline_Name": {
							"value": {
								"value": "@{pipeline().Pipeline}",
								"type": "Expression"
							},
							"type": "String"
						},
						"RowsCopied": {
							"value": {
								"value": "@{activity('Load_Retail_PIM_Delete_EDWProductPackage').output.rowsCopied}",
								"type": "Expression"
							},
							"type": "Int32"
						},
						"RowsRead": {
							"value": {
								"value": "@{activity('Load_Retail_PIM_Delete_EDWProductPackage').output.rowsRead}",
								"type": "Expression"
							},
							"type": "Int32"
						},
						"RunId": {
							"value": {
								"value": "@{pipeline().RunId}",
								"type": "Expression"
							},
							"type": "String"
						},
						"Sink": {
							"value": {
								"value": "dbo.SA_PRODUCT_PACKAGE",
								"type": "Expression"
							},
							"type": "String"
						},
						"Sink_Type": {
							"value": {
								"value": "@{activity('Load_Retail_PIM_Delete_EDWProductPackage').output.executionDetails[0].sink.type}",
								"type": "Expression"
							},
							"type": "String"
						},
						"Source": {
							"value": {
								"value": "[Retail].[EDWProductPackage]",
								"type": "Expression"
							},
							"type": "String"
						},
						"Source_Type": {
							"value": {
								"value": "@{activity('Load_Retail_PIM_Delete_EDWProductPackage').output.executionDetails[0].source.type}",
								"type": "Expression"
							},
							"type": "String"
						},
						"TriggerId": {
							"value": {
								"value": "@{pipeline().TriggerId}",
								"type": "Expression"
							},
							"type": "String"
						},
						"TriggerName": {
							"value": {
								"value": "@{pipeline().TriggerName}",
								"type": "Expression"
							},
							"type": "String"
						},
						"TriggerTime": {
							"value": {
								"value": "@{pipeline().TriggerTime}",
								"type": "Expression"
							},
							"type": "DateTime"
						},
						"TriggerType": {
							"value": {
								"value": "@{pipeline().TriggerType}",
								"type": "Expression"
							},
							"type": "String"
						}
					}
				},
				"linkedServiceName": {
					"referenceName": "semarchy_staging",
					"type": "LinkedServiceReference"
				}
			},
			{
				"name": "Teams_Failed_Notification_ProductPackage",
				"type": "ExecutePipeline",
				"dependsOn": [
					{
						"activity": "Load_Retail_PIM_Delete_EDWProductPackage",
						"dependencyConditions": [
							"Failed"
						]
					}
				],
				"userProperties": [],
				"typeProperties": {
					"pipeline": {
						"referenceName": "Notify_Teams_Channale_Pipeline",
						"type": "PipelineReference"
					},
					"waitOnCompletion": true,
					"parameters": {
						"subscription": {
							"value": "@pipeline().globalParameters.ADF_SubscriptionID",
							"type": "Expression"
						},
						"resourceGroup": "afi-edme-rg",
						"runId": {
							"value": "@pipeline().RunId",
							"type": "Expression"
						},
						"name": {
							"value": "@pipeline().Pipeline",
							"type": "Expression"
						},
						"triggerTime": {
							"value": "@activity('Load_Retail_PIM_Delete_EDWProductPackage').output.executionDetails[0].start",
							"type": "Expression"
						},
						"status": {
							"value": "@activity('Load_Retail_PIM_Delete_EDWProductPackage').output.executionDetails[0].status",
							"type": "Expression"
						},
						"message": {
							"value": "@replace(activity('Load_Retail_PIM_Delete_EDWProductPackage').error.message,'\"','')",
							"type": "Expression"
						},
						"executionEndTime": {
							"value": "@{utcnow()}",
							"type": "Expression"
						},
						"runDuration": {
							"value": "@activity('Load_Retail_PIM_Delete_EDWProductPackage').output.copyDuration",
							"type": "Expression"
						},
						"teamWebhookUrl": {
							"value": "https://masterashley.webhook.office.com/webhookb2/c31879ef-6dfb-470f-b788-de8363ae3c17@5a9d9cfd-c32e-4ac1-a9ed-fe83df4f9e4d/IncomingWebhook/147e6de5d4454f53bc64a6a9bae90283/276c88be-8000-43f8-b798-97215f5a2fda",
							"type": "Expression"
						}
					}
				}
			},
			{
				"name": "Cancel_EDWProduct_LoadId_Stored_Procedure",
				"type": "SqlServerStoredProcedure",
				"dependsOn": [
					{
						"activity": "Load_Retail_PIM_Delete_EDWProduct",
						"dependencyConditions": [
							"Failed"
						]
					}
				],
				"policy": {
					"timeout": "0.12:00:00",
					"retry": 0,
					"retryIntervalInSeconds": 30,
					"secureOutput": false,
					"secureInput": false
				},
				"userProperties": [],
				"typeProperties": {
					"storedProcedureName": "[dbo].[CANCEL_LOAD]",
					"storedProcedureParameters": {
						"P_LOAD_ID": {
							"value": {
								"value": "@variables('LoadID')",
								"type": "Expression"
							},
							"type": "Decimal"
						},
						"P_USERNAME": {
							"value": {
								"value": "semadmin",
								"type": "Expression"
							},
							"type": "String"
						}
					}
				},
				"linkedServiceName": {
					"referenceName": "semarchy_repo",
					"type": "LinkedServiceReference"
				}
			}
		],
		"variables": {
			"LoadID": {
				"type": "String"
			},
			"Date": {
				"type": "String"
			}
		},
		"folder": {
			"name": "Product_Pipelines"
		},
		"annotations": []
	}
}