{
	"name": "Stage_Phx_staging_mappings",
	"properties": {
		"description": "Refresh Dimlocation and Scoreboard store data from EDW",
		"activities": [
			{
				"name": "Scoreboard_refresh",
				"type": "Copy",
				"dependsOn": [],
				"policy": {
					"timeout": "0.12:00:00",
					"retry": 0,
					"retryIntervalInSeconds": 30,
					"secureOutput": false,
					"secureInput": false
				},
				"userProperties": [],
				"typeProperties": {
					"source": {
						"type": "SqlDWSource",
						"queryTimeout": "02:00:00",
						"partitionOption": "None"
					},
					"sink": {
						"type": "AzureSqlSink",
						"preCopyScript": "Truncate table edw.ScoreboardStore",
						"writeBehavior": "insert",
						"sqlWriterUseTableLock": false,
						"tableOption": "autoCreate",
						"disableMetricsCollection": false
					},
					"enableStaging": false,
					"translator": {
						"type": "TabularTranslator",
						"typeConversion": true,
						"typeConversionSettings": {
							"allowDataTruncation": true,
							"treatBooleanAsNumber": false
						}
					}
				},
				"inputs": [
					{
						"referenceName": "DS_ASHLEY_EDW_EDME",
						"type": "DatasetReference",
						"parameters": {
							"SchemaName": "EDME_DataFactory",
							"TableName": "ScoreboardStore"
						}
					}
				],
				"outputs": [
					{
						"referenceName": "DS_Semarchy_staging",
						"type": "DatasetReference",
						"parameters": {
							"SchemaName": "EDW",
							"TableName": "ScoreboardStore"
						}
					}
				]
			},
			{
				"name": "DimLocation Refresh",
				"type": "Copy",
				"dependsOn": [
					{
						"activity": "Scoreboard_refresh",
						"dependencyConditions": [
							"Succeeded"
						]
					}
				],
				"policy": {
					"timeout": "0.12:00:00",
					"retry": 0,
					"retryIntervalInSeconds": 30,
					"secureOutput": false,
					"secureInput": false
				},
				"userProperties": [],
				"typeProperties": {
					"source": {
						"type": "SqlDWSource",
						"queryTimeout": "02:00:00",
						"partitionOption": "None"
					},
					"sink": {
						"type": "AzureSqlSink",
						"preCopyScript": "Truncate table EDW.DIMLOCATION",
						"writeBehavior": "insert",
						"sqlWriterUseTableLock": false,
						"tableOption": "autoCreate",
						"disableMetricsCollection": false
					},
					"enableStaging": false,
					"translator": {
						"type": "TabularTranslator",
						"typeConversion": true,
						"typeConversionSettings": {
							"allowDataTruncation": true,
							"treatBooleanAsNumber": false
						}
					}
				},
				"inputs": [
					{
						"referenceName": "DS_ASHLEY_EDW_EDME",
						"type": "DatasetReference",
						"parameters": {
							"SchemaName": "EDME_DataFactory",
							"TableName": "DimLocation"
						}
					}
				],
				"outputs": [
					{
						"referenceName": "DS_Semarchy_staging",
						"type": "DatasetReference",
						"parameters": {
							"SchemaName": "EDW",
							"TableName": "DIMLOCATION"
						}
					}
				]
			},
			{
				"name": "MSA_MASTER_Refresh",
				"type": "Copy",
				"state": "Inactive",
				"onInactiveMarkAs": "Succeeded",
				"dependsOn": [
					{
						"activity": "DimLocation Refresh",
						"dependencyConditions": [
							"Succeeded"
						]
					}
				],
				"policy": {
					"timeout": "0.12:00:00",
					"retry": 0,
					"retryIntervalInSeconds": 30,
					"secureOutput": false,
					"secureInput": false
				},
				"userProperties": [],
				"typeProperties": {
					"source": {
						"type": "AzureSqlSource",
						"sqlReaderQuery": "select  distinct MSA_master_id, MSA_description from gd_msa_master",
						"queryTimeout": "02:00:00",
						"partitionOption": "None"
					},
					"sink": {
						"type": "AzureSqlSink",
						"preCopyScript": "Truncate tale retail.GD_MSA_MASTER",
						"writeBehavior": "insert",
						"sqlWriterUseTableLock": false,
						"tableOption": "autoCreate",
						"disableMetricsCollection": false
					},
					"enableStaging": false,
					"translator": {
						"type": "TabularTranslator",
						"mappings": [
							{
								"source": {
									"name": "MSA_master_id",
									"type": "String",
									"physicalType": "nvarchar"
								},
								"sink": {
									"name": "MSA_master_id",
									"type": "String",
									"physicalType": "nvarchar"
								}
							},
							{
								"source": {
									"name": "MSA_description",
									"type": "String",
									"physicalType": "nvarchar"
								},
								"sink": {
									"name": "MSA_description",
									"type": "String",
									"physicalType": "nvarchar"
								}
							}
						],
						"typeConversion": true,
						"typeConversionSettings": {
							"allowDataTruncation": true,
							"treatBooleanAsNumber": false
						}
					}
				},
				"inputs": [
					{
						"referenceName": "GD_Enterprise_REF_TABLE",
						"type": "DatasetReference"
					}
				],
				"outputs": [
					{
						"referenceName": "DS_Semarchy_staging",
						"type": "DatasetReference",
						"parameters": {
							"SchemaName": "Retail",
							"TableName": "GD_MSA_MASTER"
						}
					}
				]
			}
		],
		"folder": {
			"name": "SiteMaster"
		},
		"annotations": []
	}
}