{
	"name": "AzureSqlTable5",
	"properties": {
		"linkedServiceName": {
			"referenceName": "semarchy_dev_staging",
			"type": "LinkedServiceReference"
		},
		"annotations": [],
		"type": "AzureSqlTable",
		"schema": [
			{
				"name": "LocationNumber",
				"type": "nvarchar"
			},
			{
				"name": "Category1",
				"type": "nvarchar"
			},
			{
				"name": "Category2",
				"type": "nvarchar"
			},
			{
				"name": "Category3",
				"type": "nvarchar"
			},
			{
				"name": "Category4",
				"type": "nvarchar"
			},
			{
				"name": "Category5",
				"type": "nvarchar"
			},
			{
				"name": "Category6",
				"type": "nvarchar"
			},
			{
				"name": "Category7",
				"type": "nvarchar"
			},
			{
				"name": "Category8",
				"type": "nvarchar"
			},
			{
				"name": "Category9",
				"type": "nvarchar"
			},
			{
				"name": "Category10",
				"type": "nvarchar"
			}
		],
		"typeProperties": {
			"schema": "DAC",
			"table": "BusinessCaterogies"
		}
	}
}