{
	"name": "ds_msamaster",
	"properties": {
		"linkedServiceName": {
			"referenceName": "ls_msa_sql_database",
			"type": "LinkedServiceReference",
			"parameters": {
				"ser_server_name": "afi-edme-semarchy-dev-sql.database.windows.net",
				"database_name": "semarchy_staging",
				"user_name": "NULL",
				"db_pwd": "NULL"
			}
		},
		"parameters": {
			"schema_name": {
				"type": "String"
			},
			"table_name": {
				"type": "String"
			}
		},
		"annotations": [],
		"type": "AzureSqlTable",
		"schema": []
	}
}