{
	"name": "RestResource2",
	"properties": {
		"linkedServiceName": {
			"referenceName": "RestService1",
			"type": "LinkedServiceReference"
		},
		"parameters": {
			"ContinuationToken": {
				"type": "string"
			}
		},
		"annotations": [],
		"type": "RestResource",
		"typeProperties": {
			"relativeUrl": {
				"value": "@concat('locations-api-read/locations?AccountID=836c0e43-b4f9-41b8-80e6-fd2bee658dee&PageSize=25&ContinuationToken=',dataset().ContinuationToken)",
				"type": "Expression"
			}
		},
		"schema": []
	}
}